epoa_tools/__init__.py
epoa_tools/__version__.py
epoa_tools/complaint.py
epoa_tools/data/F700-200-000.pdf
epoa_tools/data/__init__.py
epoa_tools/job_ad.py
epoa_tools/models.py
epoa_tools/py.typed
epoa_tools/redactor.py
epoa_tools-0.0.4.dist-info/LICENSE
epoa_tools-0.0.4.dist-info/METADATA
epoa_tools-0.0.4.dist-info/WHEEL
epoa_tools-0.0.4.dist-info/entry_points.txt
epoa_tools-0.0.4.dist-info/RECORD
