Metadata-Version: 2.3
Name: epoa-tools
Version: 0.0.4
Summary: EPOA pay transparency tools
License: GPL-3.0-or-later
Author: Stephen Kent
Author-email: smkent@smkent.net
Requires-Python: >=3.9,<4.0
Classifier: Development Status :: 1 - Planning
Classifier: Operating System :: OS Independent
Classifier: Topic :: Software Development :: Libraries :: Python Modules
Classifier: Typing :: Typed
Requires-Dist: fdfgen
Requires-Dist: mdpdf
Requires-Dist: pdf-redactor
Requires-Dist: pypdf (>=3.3.0)
Requires-Dist: python-slugify
Requires-Dist: reportlab
